[
    {
        "id": 0,
        "debug_name": "Idle",
        "transitions": [
            1,
            5,
            100
        ],
        "modifiers": [
            {
                "AdjustFacing": null
            }
        ],
        "hurtboxes": [
            {
                "dimensions": [1, 2, 1]
            }
        ],
        "trigger1": [
            {
                "command": {
                    "list": [
                        [
                            ["x", "None", false]
                        ]
                    ],
                    "window": 1
                }
            },
            { "in": 5 }
        ],
        "trigger2": [
            { "in": 100 },
            { "endDuration": null }
        ],
        "trigger4": [
            { "in": 101 },
            { "endDuration": null }
        ],
        "trigger3": [
            { "in": 1},
            { 
                "command": {
                    "list": [
                        [
                            ["y", "None", false]
                        ]
                    ],
                    "window": 1

                }
            }
        ]
    },
    {
        "id": 1,
        "debug_name": "Crouch",
        "transitions": [
            0,
            101 
        ],
        "hurtboxes": [
            {
                "dimensions": [1, 1, 1]
            }
        ],
        "triggerAll": [
            {
                "command": {
                    "list": [
                        [
                            ["y", "Negative", false]
                        ]
                    ],
                    "window": 1
                }
            }
        ],
        "trigger1": [
            { "in": 101 },
            { "endDuration": null }
        ],
        "trigger2": [
            { "in": 0 }
        ]
    },
    {
        "id": 5,
        "debug_name": "Walk",
        "transitions": [
            0
        ],
        "modifiers": [
            {
                "Movement": null
            }
        ],
        "hurtboxes": [
            {
                "dimensions": [1, 1, 1]
            }
        ],
        "trigger1": [
            {
                "command": {
                    "list": [
                        [
                            ["x", "Positive", false]
                        ]
                    ],
                    "window": 1
                }
            }
        ],
        "trigger2": [
            {
                "command": {
                    "list": [
                        [
                            ["x", "Negative", false]
                        ]
                    ],
                    "window": 1
                }
            }
        ],
        "trigger3": [
            {
                "command": {
                    "list": [
                        [
                            ["x", "Positive", true]
                        ]
                    ],
                    "window": 1
                }
            }
        ],
        "trigger4": [
            {
                "command": {
                    "list": [
                        [
                            ["x", "Negative", true]
                        ]
                    ],
                    "window": 1
                }
            }
        ]
    },
    {
        "id": 100,
        "debug_name": "LP",
        "duration": 15,
        "hitboxes": [
            {
                "startFrame": 3,
                "endFrame": 6,
                "damage": 30,
                "hitstun": 18,
                "blockstun": 10,
                "dimensions": [1, 1, 1],
                "offset": [1, 0, 0]
            }
        ],
        "hurtboxes": [
            {
                "dimensions": [1, 1, 1]
            }
        ],
        "triggerAll": [
            {
                "command": {
                    "list": [
                        [
                            ["lp", "Press"]
                        ]
                    ],
                    "window": 1
                }
            }
        ]
    },
    {
        "id": 101,
        "debug_name": "2LP",
        "transitions": [
            0,
            1
        ],
        "duration": 13,
        "triggerAll": [
            {
                "command": {
                    "list": [
                        [
                            ["lp", "Press"],
                            ["y", "Negative", false]
                        ]
                    ],
                    "window": 1
                }
            }
        ]
    },
    {
        "id": 3000,
        "debug_name": "Hitstun"
    }
]